.gitignore
MANIFEST.in
README.txt
bootstrap.py
buildout.cfg
setup.py
collective/__init__.py
collective.portlet.organization.egg-info/PKG-INFO
collective.portlet.organization.egg-info/SOURCES.txt
collective.portlet.organization.egg-info/dependency_links.txt
collective.portlet.organization.egg-info/entry_points.txt
collective.portlet.organization.egg-info/namespace_packages.txt
collective.portlet.organization.egg-info/not-zip-safe
collective.portlet.organization.egg-info/requires.txt
collective.portlet.organization.egg-info/top_level.txt
collective/portlet/__init__.py
collective/portlet/organization/__init__.py
collective/portlet/organization/configure.zcml
collective/portlet/organization/organizationportlet.pt
collective/portlet/organization/organizationportlet.py
collective/portlet/organization/rebuild_i18n.sh
collective/portlet/organization/version.txt
collective/portlet/organization/locales/collective.portlet.organization.pot
collective/portlet/organization/locales/fr/LC_MESSAGES/collective.portlet.organization.po
collective/portlet/organization/profiles/default/metadata.xml
collective/portlet/organization/profiles/default/portlets.xml
collective/portlet/organization/tests/__init__.py
collective/portlet/organization/tests/base.py
collective/portlet/organization/tests/test_portlet.py
docs/HISTORY.txt
docs/INSTALL.txt
docs/LICENSE.GPL
docs/LICENSE.txt